Workbook

Sheet Instructions
B2: FOREX TRADE JOURNAL — HOW TO USE
B4: Purpose
B5: This workbook is a self-contained, offline trade journal. Open it in Excel or LibreOffice Calc (no internet or add-ins needed). Log every trade on the 'Trade Journal' tab, paste your chart screenshot into the Screenshot column, and the 'Dashboard' tab automatically calculates your stats.
B9: Color legend
B10: Yellow fill | C10: A cell you type into manually (price, pair, notes, etc.)
B11: Green fill | C11: The demo/example row on the Trade Journal tab — shows the format expected. Delete it or leave it as reference; don't count it in your stats (it's excluded automatically by row number).
B12: Grey / white cells | C12: Calculated automatically with a formula — don't type over these.
B13: Green row highlight | C13: Result = Won
B14: Red row highlight | C14: Result = Lost
B15: Amber row highlight | C15: Result = Break-even
B17: Field-by-field guide (Trade Journal tab)
B18: Trade # | C18: Auto-numbers itself — leave it alone.
B19: Date | C19: Date you entered the trade. Format: DD/MM/YYYY (or type any date, Excel formats it).
B20: Account Name | C20: e.g. Hantec Account, FTMO 100k, IC Markets Live.
B21: Pair | C21: The instrument, e.g. USDCHF, NAS100, XAUUSD.
B22: Direction | C22: Pick Buy or Sell from the dropdown.
B23: Time Frame | C23: Pick from the dropdown (1m to 1W) — the chart timeframe you traded off.
B24: Entry Price | C24: Price you opened the trade at.
B25: Stop Loss | C25: Your stop-loss price.
B26: Take Profit | C26: Your take-profit / target price.
B27: Lot Size | C27: Position size in lots (e.g. 0.10).
B28: Risk Amount ($) | C28: Dollar amount you risked (Entry-to-SL distance x lot value). Type it in manually.
B29: Risk % | C29: Auto-calculated: Risk Amount / Account Balance (fill Account Balance once at top of Dashboard).
... B37: Screenshot | C37: Paste your chart image directly into this cell (see instructions below).
B39: How to add your chart screenshot (works offline)
B40: 1. Take/save your screenshot as normal (Snipping Tool, TradingView export, phone screenshot transferred over, etc.).
B41: 2. Click the Screenshot cell for that trade row on the Trade Journal tab.
B42: 3. Excel: Insert tab -> Pictures -> This Device -> pick the file. LibreOffice Calc: Insert -> Image.
B43: 4. Drag the image corner to resize it so it sits inside the row/column, matching row 2's demo image.
B44: 5. This all works fully offline once the image file is on your device — no internet needed.
B46: Tabs in this workbook
B47: Trade Journal | C47: Your main log — one row per trade, screenshot included.
B48: Dashboard | C48: Auto-calculated stats: win rate, total P/L, best/worst pairs, equity curve.

Sheet Trade Journal
A1: TRADE JOURNAL
A2: Trade # | B2: Date | C2: Account Name | D2: Pair | E2: Direction | F2: Time Frame | G2: Entry Price | H2: Stop Loss | I2: Take Profit | J2: Lot Size | K2: Risk Amount ($) | L2: Risk % | M2: Result | N2: P/L ($) | O2: P/L (Pips) | P2: Reward:Risk | Q2: Strategy / Setup | R2: Psychology | S2: Notes / Lessons | T2: Screenshot
A3: 1 | B3: 46213 | C3: Hantec Account | D3: USDCHF | E3: Buy | F3: 1h | G3: 0.8845 | H3: 0.881 | I3: 0.893 | J3: 0.1 | K3: 35 | L3: =IFERROR(K3/Dashboard!$C$4,"") -> 0.0035 | M3: Won | N3: 62.5 | O3: 85 | P3: =IFERROR(ABS(I3-G3)/ABS(G3-H3),"") -> 2.4285714 | Q3: Breakout Retest | R3: Disciplined | S3: Waited for candle close above resistance before entering. Followed plan exactly, took partial profit at 1:1.
A4: =IF(B4="","",ROW()-3) -> 1 | B4: 14/07/2026 | C4: FTMO 10K DEMO | D4: S&P 500 | E4: Buy | F4: 1h | G4: 7508.2 | H4: 7480.3 | I4: 7580 | J4: 5.01 | K4: 50 | L4: =IFERROR(K4/Dashboard!$C$4,"") -> 0.005 | M4: Won | N4: 103.31 | O4: 731 | P4: =IFERROR(ABS(I4-G4)/ABS(G4-H4),"") -> 2.5734767 | Q4: Market Structure & RSI | R4: Disciplined | S4: Analysed 1H and entry at 15min after the formation of the regular | T4: #VALUE!
A5: =IF(B5="","",ROW()-3) | L5: =IFERROR(K5/Dashboard!$C$4,"") -> 0 | P5: =IFERROR(ABS(I5-G5)/ABS(G5-H5),"")
A6: =IF(B6="","",ROW()-3) | L6: =IFERROR(K6/Dashboard!$C$4,"") -> 0 | P6: =IFERROR(ABS(I6-G6)/ABS(G6-H6),"")
A7: =IF(B7="","",ROW()-3) | L7: =IFERROR(K7/Dashboard!$C$4,"") -> 0 | P7: =IFERROR(ABS(I7-G7)/ABS(G7-H7),"")
A8: =IF(B8="","",ROW()-3) | L8: =IFERROR(K8/Dashboard!$C$4,"") -> 0 | P8: =IFERROR(ABS(I8-G8)/ABS(G8-H8),"")
A9: =IF(B9="","",ROW()-3) | L9: =IFERROR(K9/Dashboard!$C$4,"") -> 0 | P9: =IFERROR(ABS(I9-G9)/ABS(G9-H9),"")
A10: =IF(B10="","",ROW()-3) | L10: =IFERROR(K10/Dashboard!$C$4,"") -> 0 | P10: =IFERROR(ABS(I10-G10)/ABS(G10-H10),"")
A11: =IF(B11="","",ROW()-3) | L11: =IFERROR(K11/Dashboard!$C$4,"") -> 0 | P11: =IFERROR(ABS(I11-G11)/ABS(G11-H11),"")
A12: =IF(B12="","",ROW()-3) | L12: =IFERROR(K12/Dashboard!$C$4,"") -> 0 | P12: =IFERROR(ABS(I12-G12)/ABS(G12-H12),"")
A13: =IF(B13="","",ROW()-3) | L13: =IFERROR(K13/Dashboard!$C$4,"") -> 0 | P13: =IFERROR(ABS(I13-G13)/ABS(G13-H13),"")
A14: =IF(B14="","",ROW()-3) | L14: =IFERROR(K14/Dashboard!$C$4,"") -> 0 | P14: =IFERROR(ABS(I14-G14)/ABS(G14-H14),"")
A15: =IF(B15="","",ROW()-3) | L15: =IFERROR(K15/Dashboard!$C$4,"") -> 0 | P15: =IFERROR(ABS(I15-G15)/ABS(G15-H15),"")
A16: =IF(B16="","",ROW()-3) | L16: =IFERROR(K16/Dashboard!$C$4,"") -> 0 | P16: =IFERROR(ABS(I16-G16)/ABS(G16-H16),"")
... A203: =IF(B203="","",ROW()-3) | L203: =IFERROR(K203/Dashboard!$C$4,"") -> 0 | P203: =IFERROR(ABS(I203-G203)/ABS(G203-H203),"")

Sheet Dashboard
B2: DASHBOARD
B4: Account Balance ($) | C4: 10000
B5: (used to calculate Risk % on the Trade Journal tab — type your real balance in the yellow cell above)
B7: KEY STATISTICS
B8: Total Trades Logged | C8: =COUNTA('Trade Journal'!B4:B203) -> 1
B9: Wins | C9: =COUNTIF('Trade Journal'!M4:M203,"Won") -> 1
B10: Losses | C10: =COUNTIF('Trade Journal'!M4:M203,"Lost") -> 0
B11: Break-even | C11: =COUNTIF('Trade Journal'!M4:M203,"Break-even") -> 0
B12: Win Rate | C12: =IFERROR(C8/(C8+C9),"") -> 0.5
B13: Total Net P/L ($) | C13: =SUM('Trade Journal'!N4:N203) -> 103.31
B14: Average Win ($) | C14: =IFERROR(AVERAGEIF('Trade Journal'!M4:M203,"Won",'Trade Journal'!N4:N203),"") -> 103.31
B15: Average Loss ($) | C15: =IFERROR(AVERAGEIF('Trade Journal'!M4:M203,"Lost",'Trade Journal'!N4:N203),"")
B16: Average Reward:Risk | C16: =IFERROR(AVERAGE('Trade Journal'!P4:P203),"") -> 2.5734767
B17: Largest Win ($) | C17: =IFERROR(MAX('Trade Journal'!N4:N203),"") -> 103.31
B18: Largest Loss ($) | C18: =IFERROR(MIN('Trade Journal'!N4:N203),"") -> 103.31
B19: Current Balance ($) | C19: =C4+C13 -> 10103.31
B21: PERFORMANCE BY PAIR
B22: Pair | C22: Trades | D22: Wins | E22: Win Rate | F22: Net P/L ($)
B23: USDCHF | C23: =COUNTIF('Trade Journal'!$D$4:$D$203,$B23) -> 0 | D23: =COUNTIFS('Trade Journal'!$D$4:$D$203,$B23,'Trade Journal'!$M$4:$M$203,"Won") -> 0 | E23: =IFERROR(D23/C23,"") | F23: =SUMIF('Trade Journal'!$D$4:$D$203,$B23,'Trade Journal'!$N$4:$N$203) -> 0
B24: NAS100 | C24: =COUNTIF('Trade Journal'!$D$4:$D$203,$B24) -> 0 | D24: =COUNTIFS('Trade Journal'!$D$4:$D$203,$B24,'Trade Journal'!$M$4:$M$203,"Won") -> 0 | E24: =IFERROR(D24/C24,"") | F24: =SUMIF('Trade Journal'!$D$4:$D$203,$B24,'Trade Journal'!$N$4:$N$203) -> 0
B25: USDJPY | C25: =COUNTIF('Trade Journal'!$D$4:$D$203,$B25) -> 0 | D25: =COUNTIFS('Trade Journal'!$D$4:$D$203,$B25,'Trade Journal'!$M$4:$M$203,"Won") -> 0 | E25: =IFERROR(D25/C25,"") | F25: =SUMIF('Trade Journal'!$D$4:$D$203,$B25,'Trade Journal'!$N$4:$N$203) -> 0
B26: GBPJPY | C26: =COUNTIF('Trade Journal'!$D$4:$D$203,$B26) -> 0 | D26: =COUNTIFS('Trade Journal'!$D$4:$D$203,$B26,'Trade Journal'!$M$4:$M$203,"Won") -> 0 | E26: =IFERROR(D26/C26,"") | F26: =SUMIF('Trade Journal'!$D$4:$D$203,$B26,'Trade Journal'!$N$4:$N$203) -> 0
B27: EURUSD | C27: =COUNTIF('Trade Journal'!$D$4:$D$203,$B27) -> 0 | D27: =COUNTIFS('Trade Journal'!$D$4:$D$203,$B27,'Trade Journal'!$M$4:$M$203,"Won") -> 0 | E27: =IFERROR(D27/C27,"") | F27: =SUMIF('Trade Journal'!$D$4:$D$203,$B27,'Trade Journal'!$N$4:$N$203) -> 0
B28: XAUUSD | C28: =COUNTIF('Trade Journal'!$D$4:$D$203,$B28) -> 0 | D28: =COUNTIFS('Trade Journal'!$D$4:$D$203,$B28,'Trade Journal'!$M$4:$M$203,"Won") -> 0 | E28: =IFERROR(D28/C28,"") | F28: =SUMIF('Trade Journal'!$D$4:$D$203,$B28,'Trade Journal'!$N$4:$N$203) -> 0
B29: GBPUSD | C29: =COUNTIF('Trade Journal'!$D$4:$D$203,$B29) -> 0 | D29: =COUNTIFS('Trade Journal'!$D$4:$D$203,$B29,'Trade Journal'!$M$4:$M$203,"Won") -> 0 | E29: =IFERROR(D29/C29,"") | F29: =SUMIF('Trade Journal'!$D$4:$D$203,$B29,'Trade Journal'!$N$4:$N$203) -> 0
B30: US30 | C30: =COUNTIF('Trade Journal'!$D$4:$D$203,$B30) -> 0 | D30: =COUNTIFS('Trade Journal'!$D$4:$D$203,$B30,'Trade Journal'!$M$4:$M$203,"Won") -> 0 | E30: =IFERROR(D30/C30,"") | F30: =SUMIF('Trade Journal'!$D$4:$D$203,$B30,'Trade Journal'!$N$4:$N$203) -> 0
B31: AUDUSD | C31: =COUNTIF('Trade Journal'!$D$4:$D$203,$B31) -> 0 | D31: =COUNTIFS('Trade Journal'!$D$4:$D$203,$B31,'Trade Journal'!$M$4:$M$203,"Won") -> 0 | E31: =IFERROR(D31/C31,"") | F31: =SUMIF('Trade Journal'!$D$4:$D$203,$B31,'Trade Journal'!$N$4:$N$203) -> 0
B32: USDCAD | C32: =COUNTIF('Trade Journal'!$D$4:$D$203,$B32) -> 0 | D32: =COUNTIFS('Trade Journal'!$D$4:$D$203,$B32,'Trade Journal'!$M$4:$M$203,"Won") -> 0 | E32: =IFERROR(D32/C32,"") | F32: =SUMIF('Trade Journal'!$D$4:$D$203,$B32,'Trade Journal'!$N$4:$N$203) -> 0
B34: Edit the pair names above (yellow cells) to match what you actually trade — the stats update automatically.
B36: WANT A CHART? (equity curve / win-loss chart)
B37: Once you've logged some trades, select the P/L ($) column on the Trade Journal tab (just the filled rows) and use Insert > Chart (Line or Column) — this builds a live chart from your real data and works fully offline. A pre-built chart isn't included here because it would otherwise show 200 empty rows until your journal fills up.
